cointiger_sdk/CoinTiger.py
cointiger_sdk/CoinTigerWebsocket.py
cointiger_sdk/__init__.py
cointiger_sdk/const.py
cointiger_sdk/function.py
cointiger_sdk-0.1.2.dist-info/METADATA
cointiger_sdk-0.1.2.dist-info/RECORD
cointiger_sdk-0.1.2.dist-info/WHEEL
cointiger_sdk-0.1.2.dist-info/top_level.txt
test/rest_demo.py
test/websocket_demo.py
